vytools/__init__.py
vytools/episode.py
vytools/object.py
vytools/utils.py
vytools-0.10.0.dist-info/METADATA
vytools-0.10.0.dist-info/WHEEL
vytools-0.10.0.dist-info/entry_points.txt
vytools-0.10.0.dist-info/top_level.txt
vytools-0.10.0.dist-info/RECORD
