Metadata-Version: 2.1
Name: vytools
Version: 0.10.0
Summary: Tools for working with vy
Home-page: https://github.com/NateBu/vyengine
Author: Nate Bunderson
Author-email: nbunderson@gmail.com
License: MIT
Keywords: vy,vytools
Platform: UNKNOWN
Classifier: Programming Language :: Python
Classifier: Development Status :: 2 - Pre-Alpha
Classifier: Intended Audience :: Developers
Classifier: License :: OSI Approved :: MIT License
Classifier: Operating System :: OS Independent
Classifier: Programming Language :: Python :: 3
Classifier: Topic :: Other/Nonlisted Topic
Requires-Python: >=3.6
Requires-Dist: cerberus
